openitcr-0.0.2.data/scripts/openitcr
tests/__init__.py
openitcr-0.0.2.dist-info/LICENSE
openitcr-0.0.2.dist-info/METADATA
openitcr-0.0.2.dist-info/WHEEL
openitcr-0.0.2.dist-info/top_level.txt
openitcr-0.0.2.dist-info/RECORD
