Metadata-Version: 2.1
Name: openitcr
Version: 0.0.2
Summary: Open Information Technology Classroom
Home-page: https://github.com/larryw3i/openitcr
Author: larryw3i
Author-email: larryw3i@163.com
License: GPL-3.0-or-later
Download-URL: https://github.com/larryw3i/openitcr
Project-URL: Code, https://github.com/larryw3i/openitcr
Project-URL: Issue tracker, https://github.com/larryw3i/openitcr/issues
Project-URL: Documentation, https://github.com/larryw3i/openitcr/docs/docs.md
Platform: UNKNOWN
Classifier: License :: OSI Approved :: GNU General Public License v3 or later (GPLv3+)
Classifier: Programming Language :: Python :: 3.7
Classifier: Programming Language :: Python :: 3.8
Requires-Python: >=3.7
Requires-Dist: Babel (==2.9.0)
Requires-Dist: pytz (==2021.1)
Requires-Dist: toml (==0.10.2)
